ChinnuAi/KalaQuantum.py
ChinnuAi/__init__.py
ChinnuAi-1.2.5.dist-info/METADATA
ChinnuAi-1.2.5.dist-info/WHEEL
ChinnuAi-1.2.5.dist-info/top_level.txt
ChinnuAi-1.2.5.dist-info/RECORD
